datastructure/__init__.py
datastructure/__version__.py
datastructure/datastructure.py
datastructure/datafiles/__init__.py
datastructure/datafiles/interface.py
datastructure/datafiles/register.py
datastructure/datafiles/formats/__init__.py
datastructure/datafiles/formats/abstractdatafileformat.py
datastructure/datafiles/formats/datafileformats.py
datastructure/datafiles/formats/jsondatafile.py
datastructure/datafiles/formats/yamldatafile.py
serializable_datastructure-0.2.0.dist-info/licenses/LICENSE
serializable_datastructure-0.2.0.dist-info/METADATA
serializable_datastructure-0.2.0.dist-info/WHEEL
serializable_datastructure-0.2.0.dist-info/top_level.txt
serializable_datastructure-0.2.0.dist-info/RECORD
