Metadata-Version: 2.4
Name: serializable-datastructure
Version: 0.2.0
Summary: Serializable Datastructure is a Python library that allows you to convert a Python object into any data file format and vice versa (currently JSON & YAML).
Author-email: CeREF Technique <developpement@ceref.be>, RocaroDev <rocarodevelopment@gmail.com>
License:                     GNU AFFERO GENERAL PUBLIC LICENSE
Keywords: serializable,datastructure,json,yaml,data,structure,serialization,deserialization,convert,conversion,file,format,pandas,pyyaml
Classifier: Development Status :: 4 - Beta
Classifier: Intended Audience :: Developers
Classifier: License :: OSI Approved :: GNU Affero General Public License v3 or later (AGPLv3+)
Requires-Python: >=3.10
License-File: LICENSE
Requires-Dist: pandas>=1.4.4
Requires-Dist: PyYAML>=6.0
Dynamic: license-file
